setup.py
obviously/__init__.py
obviously/the.py
obviously.egg-info/PKG-INFO
obviously.egg-info/SOURCES.txt
obviously.egg-info/dependency_links.txt
obviously.egg-info/top_level.txt