Metadata-Version: 1.0
Name: obviously
Version: 0.1
Summary: Rspec-style test helper, but with more attitude.
Home-page: http://github.com/haaksmash/obviously
Author: Haak Saxberg
Author-email: haak.erling@gmail.com
License: UNKNOWN
Platform: UNKNOWN
